captcha_prune/__init__.py
captcha_prune/asgi.py
captcha_prune/models.py
captcha_prune/payloads.py
captcha_prune/settings.py
captcha_prune/urls.py
captcha_prune/views.py
captcha_prune/wsgi.py
commons/base_model.py
commons/decorators.py
captcha_prune-1.0.0.dist-info/METADATA
captcha_prune-1.0.0.dist-info/WHEEL
captcha_prune-1.0.0.dist-info/entry_points.txt
captcha_prune-1.0.0.dist-info/top_level.txt
captcha_prune-1.0.0.dist-info/RECORD
