Metadata-Version: 2.4
Name: captcha_prune
Version: 1.0.0
Summary: A tool to protect formulaire from spam.
Author-email: Arnout <bastien@prune.sh>
Project-URL: Made_by, https://prune.sh/
Keywords: captcha,django,code-quality
Classifier: Programming Language :: Python :: 3
Classifier: License :: OSI Approved :: MIT License
Classifier: Operating System :: OS Independent
Requires-Python: <4.0,>=3.12
Requires-Dist: django>=5.2
Requires-Dist: psycopg2-binary>=2.9.10
Requires-Dist: pydantic>=2.11.4
Requires-Dist: pydantic-settings>=2.9.1
